peter_parquet/__init__.py
peter_parquet/cliparquet.py
peter_parquet/main.py
peter_parquet-0.3.0.dist-info/entry_points.txt
peter_parquet-0.3.0.dist-info/WHEEL
peter_parquet-0.3.0.dist-info/METADATA
peter_parquet-0.3.0.dist-info/RECORD
